LICENSE
th2_check2_recon/__init__.py
th2_check2_recon/builders.py
th2_check2_recon/new.py
th2_check2_recon/recon.py
th2_check2_recon/recon_message.py
th2_check2_recon/rule.py
th2_check2_recon/util/__init__.py
th2_check2_recon/util/cache/__init__.py
th2_check2_recon/util/cache/cache.py
th2_check2_recon/util/cache/message_groups.py
th2_check2_recon/util/cache/storages.py
th2_check2_recon/util/configuration.py
th2_check2_recon/util/events/__init__.py
th2_check2_recon/util/events/event_manager.py
th2_check2_recon/util/events/event_producers.py
th2_check2_recon/util/handler.py
th2_check2_recon/util/message_processor.py
th2_check2_recon/util/process_units.py
th2_check2_recon/utils.py
th2_check2_recon-4.0.0.dev3884233338.dist-info/WHEEL
th2_check2_recon-4.0.0.dev3884233338.dist-info/LICENSE
th2_check2_recon-4.0.0.dev3884233338.dist-info/METADATA
th2_check2_recon-4.0.0.dev3884233338.dist-info/RECORD
